katzenpost_thinclient/__init__.py
katzenpost_thinclient-0.0.11.dist-info/METADATA
katzenpost_thinclient-0.0.11.dist-info/WHEEL
katzenpost_thinclient-0.0.11.dist-info/licenses/LICENSE
katzenpost_thinclient-0.0.11.dist-info/RECORD
