Metadata-Version: 2.4
Name: katzenpost_thinclient
Version: 0.0.11
Summary: A thinclient for the Katzenpost client daemon
Project-URL: Homepage, https://katzenpost.network/
Project-URL: Issues, https://github.com/katzenpost/thin_client/issues
Author-email: David Stainton <dstainton415@gmail.com>
License-File: LICENSE
Classifier: Intended Audience :: Developers
Classifier: License :: OSI Approved :: GNU Affero General Public License v3
Classifier: Operating System :: OS Independent
Classifier: Programming Language :: Python :: 3
Classifier: Topic :: Security :: Cryptography
Requires-Python: >=3.8
Requires-Dist: asyncio~=3.4.3
Requires-Dist: cbor2~=5.6.5
Requires-Dist: coloredlogs~=15.0.1
Requires-Dist: pprintpp~=0.4.0
Requires-Dist: toml~=0.10.2
Provides-Extra: dev
Requires-Dist: mypy; extra == 'dev'
Requires-Dist: types-toml; extra == 'dev'
Provides-Extra: test
Requires-Dist: pytest; extra == 'test'
Requires-Dist: pytest-asyncio; extra == 'test'
Requires-Dist: pytest-cov; extra == 'test'
